{
  "nctId": "NCT02959138",
  "briefTitle": "Pharmacokinetics of Lanraplenib in Adults With Impaired Renal Function",
  "officialTitle": "A Phase 1 Open-Label Study to Evaluate the Pharmacokinetics of GS-9876 in Subjects With Impaired Renal Function",
  "protocolDocument": {
    "nctId": "NCT02959138",
    "filename": "Prot_000.pdf",
    "label": "Study Protocol: Amendment 1",
    "date": "2017-01-09",
    "uploadDate": "2019-09-09T07:03",
    "size": 1205965,
    "downloadUrl": "https://clinicaltrials.gov/api/v2/studies/NCT02959138/document/Prot_000.pdf",
    "hasProtocol": true,
    "hasSap": false,
    "hasIcf": false
  },
  "phase": [
    "PHASE1"
  ],
  "studyType": "INTERVENTIONAL",
  "allocation": "NON_RANDOMIZED",
  "interventionModel": "PARALLEL",
  "masking": "NONE",
  "enrollmentInfo": {
    "enrollmentCount": 36,
    "enrollmentType": "ACTUAL"
  },
  "timeline": {
    "startDate": "2016-11-21",
    "completionDate": "2018-10-05",
    "primaryCompletionDate": "2018-10-05",
    "firstSubmitDate": "2016-11-07",
    "firstPostDate": "2016-11-08"
  },
  "eligibilityCriteria": {
    "criteria": "Key Inclusion Criteria:\n\nAll Individuals\n\n* Have the ability to understand and sign a written informed consent form (ICF), which must be obtained prior to initiation of study procedures\n* Have a calculated body mass index (BMI) of ≥ 18 kg/m\\^2 and ≤ 36 kg/m\\^2 at screening\n* Females of childbearing potential must have a negative pregnancy test at screening and clinic admission (Day -1).\n* Individuals have not donated blood within 56 days of study entry or plasma within 7 days of study entry and must refrain from blood donation from clinic admission, throughout the study period, and continuing for at least 30 days following the last dose of study drug.\n* Have either a normal 12-lead electrocardiogram (ECG) or one with abnormalities that are considered clinically insignificant by the investigator in consultation with the sponsor\n* Must, in the opinion of the investigator, be in good health based upon medical history and physical examination, including vital signs\n\nFor Individuals with Renal Impairment\n\n* Must have diagnosis of chronic (\\> 6 months), stable renal impairment with no clinically significant change in renal function status within 90 days prior to study drug administration (Day 1).\n* Have a creatinine clearance (CLcr) \\< 90 mL/min (using the Cockcroft-Gault method) based on serum creatinine and actual body weight as measured at screening.\n\nFor Healthy Matched Controlled Individuals (Individuals with Normal Renal Function)\n\n* Have a CLcr ≥ 90 mL/min (using the Cockcroft-Gault method) based on serum creatinine and actual body weight as measured at screening\n* Match in age (± 10 years), gender, and body mass index (± 20%, 18 kg/m\\^2 ≤ BMI ≤ 36 kg/m\\^2).\n\nKey Exclusion Criteria:\n\n* Be a lactating female\n* Have received any investigational compound within 30 days prior to study dosing\n* Have current alcohol or substance abuse judged by the investigator to potentially interfere with individual's compliance or individual's safety as judged by the investigator\n* Have a positive test result for human immunodeficiency virus type 1 (HIV-1) antibody, hepatitis B surface antigen (HBsAg), hepatitis B core antibody (HBcAb), or hepatitis C virus (HCV) antibody\n* Have poor venous access that limits phlebotomy\n\nFor Individuals with Renal Impairment\n\n* Require or are anticipated to require dialysis within 90 days of study dosing\n* Require during the study or have received moderate or strong inhibitors or inducers of cytochrome P450 (CYP) 3A within 2 weeks prior to study drug administration.\n\nFor Healthy Matched Controlled Individuals (Individuals with Normal Renal Function)\n\n* Have taken any prescription medications or over-the-counter medications, including herbal products and antacids, within 28 days prior to start of study drug dosing, with the exception of vitamins and/or acetaminophen and/or ibuprofen and/or hormonal contraceptive medications and/or stable hormone replacement therapy in peri- /post-menopausal female\n\nNote: Other protocol defined Inclusion/Exclusion criteria may apply.",
    "healthyVolunteers": true,
    "sex": "ALL",
    "minimumAge": "18 Years",
    "maximumAge": "75 Years",
    "stdAges": [
      "ADULT",
      "OLDER_ADULT"
    ]
  },
  "endpoints": {
    "primary": [
      {
        "measure": "Pharmacokinetic (PK) Parameter: AUClast of Lanraplenib Presented Based on Range of CLcr",
        "description": "AUClast is defined as the concentration of drug from time zero to the last observable concentration. CLcr was estimated using the CG equation for renal function as recommended by the FDA and international guidance documents. CG equation:\n\nFor men: CLcr (mL/min) = (\\[140-age in years\\] × \\[body weight in kg\\])/(72 × serum creatinine in mg/dL)\n\nFor women: CLcr (mL/min) = 0.85 × (\\[140-age in years\\] × \\[body weight in kg\\])/(72 × serum creatinine in mg/dL)\n\nParticipants were classified based on estimated CLcr as:\n\nModerate renal impairment: CLcr 30-59 mL/min\n\nSevere renal impairment: CLcr 15-29 mL/min\n\nHealthy control: CLcr ≥ 90 mL/min",
        "timeFrame": "0 (predose), 0.5, 1, 2, 3, 4, 5, 6, 8, 12, 16, 24, 36, 48, 60, 72, 96 and 120 hours postdose on Day 1"
      },
      {
        "measure": "PK Parameter: AUCinf of Lanraplenib Presented Based on Range of CLcr",
        "description": "AUCinf is defined as the concentration of drug extrapolated to infinite time. CLcr was estimated using the CG equation for renal function as recommended by the FDA and international guidance documents. CG equation:\n\nFor men: CLcr (mL/min) = (\\[140-age in years\\] × \\[body weight in kg\\])/(72 × serum creatinine in mg/dL)\n\nFor women: CLcr (mL/min) = 0.85 × (\\[140-age in years\\] × \\[body weight in kg\\])/(72 × serum creatinine in mg/dL)\n\nParticipants were classified based on estimated CLcr as:\n\nModerate renal impairment: CLcr 30-59 mL/min\n\nSevere renal impairment: CLcr 15-29 mL/min\n\nHealthy control: CLcr ≥ 90 mL/min",
        "timeFrame": "0 (predose), 0.5, 1, 2, 3, 4, 5, 6, 8, 12, 16, 24, 36, 48, 60, 72, 96 and 120 hours postdose on Day 1"
      },
      {
        "measure": "PK Parameter: Cmax of Lanraplenib Presented Based on Range of CLcr",
        "description": "Cmax is defined as the maximum concentration of drug. CLcr was estimated using the CG equation for renal function as recommended by the FDA and international guidance documents. CG equation:\n\nFor men: CLcr (mL/min) = (\\[140-age in years\\] × \\[body weight in kg\\])/(72 × serum creatinine in mg/dL)\n\nFor women: CLcr (mL/min) = 0.85 × (\\[140-age in years\\] × \\[body weight in kg\\])/(72 × serum creatinine in mg/dL)\n\nParticipants were classified based on estimated CLcr as:\n\nModerate renal impairment: CLcr 30-59 mL/min\n\nSevere renal impairment: CLcr 15-29 mL/min\n\nHealthy control: CLcr ≥ 90 mL/min",
        "timeFrame": "0 (predose), 0.5, 1, 2, 3, 4, 5, 6, 8, 12, 16, 24, 36, 48, 60, 72, 96 and 120 hours postdose on Day 1"
      }
    ],
    "secondary": [
      {
        "measure": "Percentage of Participants Who Experienced Treatment-Emergent Adverse Events",
        "timeFrame": "Day 1 up to Day 31"
      },
      {
        "measure": "Percentage of Participants Who Experienced Graded Laboratory Abnormalities",
        "description": "Treatment-emergent laboratory abnormalities were defined as values that increase at least one toxicity grade from baseline. The most severe graded abnormality from all tests was counted for each participant. The criteria used for grading was Common Terminology Criteria for Adverse Events (CTCAE) v 4.03.",
        "timeFrame": "Day 1 up to Day 31"
      }
    ],
    "other": []
  },
  "complexityMetrics": {
    "eligibilityCriteria": {
      "inclusionCount": 1,
      "exclusionCount": 1,
      "totalCount": 2
    },
    "endpoints": {
      "primaryCount": 3,
      "secondaryCount": 2,
      "otherCount": 0,
      "totalCount": 5
    },
    "studyDesign": {
      "phases": [
        "PHASE1"
      ],
      "isRandomized": false,
      "isMasked": false,
      "interventionModel": "PARALLEL"
    },
    "overallComplexityScore": 44,
    "complexityCategory": "Moderate"
  },
  "collectionDate": "2025-09-22T02:30:07.562Z",
  "dataSource": "ClinicalTrials.gov API v2 - Comprehensive Collection"
}